procenty/__init__.py
procenty/inflacja.py
procenty/inwestycja.py
procenty/kredyt.py
procenty/miary.py
procenty/stopy.py
procenty/utils/__init__.py
procenty/utils/create_kredyt.py
procenty/utils/generate_model.py
procenty/utils/inne.py
procenty-0.1.32.dist-info/LICENSE
procenty-0.1.32.dist-info/METADATA
procenty-0.1.32.dist-info/WHEEL
procenty-0.1.32.dist-info/RECORD
